instant_clip_tokenizer-0.1.1.dist-info/METADATA
instant_clip_tokenizer-0.1.1.dist-info/WHEEL
instant_clip_tokenizer/__init__.py
instant_clip_tokenizer/instant_clip_tokenizer.cpython-38-x86_64-linux-gnu.so
instant_clip_tokenizer-0.1.1.dist-info/RECORD
