Metadata-Version: 2.1
Name: instant-clip-tokenizer
Version: 0.1.1
Requires-Dist: numpy >=1.16.0
Summary: Fast text tokenizer for the CLIP neural network
Home-Page: https://github.com/instant-labs/instant-clip-tokenizer
License: MIT
Project-URL: Source Code, https://github.com/instant-labs/instant-clip-tokenizer
